colorone/__init__.py
colorone/ansi.py
colorone/colors.py
colorone/core.py
colorone/styles.py
colorone/terminal.py
colorone/utils.py
colorone/win32.py
colorone/winterm.py
colorone-1.2.dist-info/LICENSE.txt
colorone-1.2.dist-info/METADATA
colorone-1.2.dist-info/WHEEL
colorone-1.2.dist-info/top_level.txt
colorone-1.2.dist-info/RECORD
