Metadata-Version: 2.1
Name: colorone
Version: 1.2
Summary: This is a simple package to handle easily various colors in either the PyGame (RGB) format or the OpenCV (BGR) format. Default mode is PyGame.
Author: Lauren Jackson
Author-email: laurendevyork@gmail.com
Classifier: Programming Language :: Python :: 3
Classifier: License :: OSI Approved :: MIT License
Classifier: Operating System :: OS Independent
License-File: LICENSE.txt
